sqlite_wikidata/__about__.py
sqlite_wikidata/__init__.py
sqlite_wikidata/build_index.py
sqlite_wikidata/db.py
sqlite_wikidata/process_dump.py
sqlite_wikidata-0.0.1.dist-info/METADATA
sqlite_wikidata-0.0.1.dist-info/WHEEL
sqlite_wikidata-0.0.1.dist-info/licenses/LICENSE.txt
sqlite_wikidata-0.0.1.dist-info/RECORD
